gcallm/__init__.py
gcallm/agent.py
gcallm/cli.py
gcallm/config.py
gcallm/conflicts.py
gcallm/formatter.py
gcallm/helpers/__init__.py
gcallm/helpers/input.py
gcallm/helpers/screenshot.py
gcallm-0.1.1.dist-info/METADATA
gcallm-0.1.1.dist-info/WHEEL
gcallm-0.1.1.dist-info/entry_points.txt
gcallm-0.1.1.dist-info/licenses/LICENSE
gcallm-0.1.1.dist-info/RECORD
