Metadata-Version: 2.4
Name: gcallm
Version: 0.1.1
Summary: Simple CLI to add events to Google Calendar using Claude and natural language
Project-URL: Homepage, https://github.com/WarrenZhu050413/gcallm
Project-URL: Repository, https://github.com/WarrenZhu050413/gcallm
Project-URL: Issues, https://github.com/WarrenZhu050413/gcallm/issues
Author-email: Warren Zhu <wzhu@college.harvard.edu>
License: MIT
License-File: LICENSE
Keywords: calendar,claude,cli,google-calendar,llm,mcp,natural-language
Classifier: Development Status :: 4 - Beta
Classifier: Environment :: Console
Classifier: Intended Audience :: Developers
Classifier: Intended Audience :: End Users/Desktop
Classifier: License :: OSI Approved :: MIT License
Classifier: Operating System :: OS Independent
Classifier: Programming Language :: Python :: 3
Classifier: Programming Language :: Python :: 3.10
Classifier: Programming Language :: Python :: 3.11
Classifier: Programming Language :: Python :: 3.12
Classifier: Topic :: Office/Business :: Scheduling
Classifier: Topic :: Utilities
Requires-Python: >=3.10
Requires-Dist: claude-agent-sdk>=0.1.0
Requires-Dist: click>=8.0.0
Requires-Dist: python-dateutil>=2.8.0
Requires-Dist: rich>=13.0.0
Requires-Dist: shellingham>=1.0.0
Requires-Dist: typer>=0.9.0
